GeoEco/ArcGIS.py
GeoEco/ArcToolbox.py
GeoEco/BatchProcessing.py
GeoEco/Dependencies.py
GeoEco/DynamicDocString.py
GeoEco/Exceptions.py
GeoEco/Internationalization.py
GeoEco/Logging.py
GeoEco/Metadata.py
GeoEco/_MetadataUtils.cp310-win_amd64.pyd
GeoEco/__init__.py
GeoEco/_version.py
GeoEco/ArcToolbox/Marine Geospatial Ecology Tools.atbx
GeoEco/Configuration/Logging.ini
GeoEco/DataManagement/ArcGISRasters.py
GeoEco/DataManagement/Directories.py
GeoEco/DataManagement/Fields.py
GeoEco/DataManagement/Files.py
GeoEco/DataManagement/__init__.py
GeoEco/DataProducts/CMEMS.py
GeoEco/DataProducts/__init__.py
GeoEco/DataProducts/NASA/__init__.py
GeoEco/DataProducts/NASA/Earthdata/_CMRGranuleSearcher.py
GeoEco/DataProducts/NASA/Earthdata/_CMRGranuleSearcherMetadata.py
GeoEco/DataProducts/NASA/Earthdata/__init__.py
GeoEco/DataProducts/NASA/PODAAC/_GHRSSTLevel4.py
GeoEco/DataProducts/NASA/PODAAC/_GHRSSTLevel4Granules.py
GeoEco/DataProducts/NASA/PODAAC/_GHRSSTLevel4GranulesMetadata.py
GeoEco/DataProducts/NASA/PODAAC/_GHRSSTLevel4Metadata.py
GeoEco/DataProducts/NASA/PODAAC/__init__.py
GeoEco/DataProducts/NOAA/ClimateIndices.py
GeoEco/DataProducts/NOAA/__init__.py
GeoEco/Datasets/HDF4.py
GeoEco/Datasets/NetCDF.py
GeoEco/Datasets/SQLite.py
GeoEco/Datasets/_CollectibleObject.py
GeoEco/Datasets/_CollectibleObjectMetadata.py
GeoEco/Datasets/_Cursors.py
GeoEco/Datasets/_CursorsMetadata.py
GeoEco/Datasets/_Database.py
GeoEco/Datasets/_DatabaseMetadata.py
GeoEco/Datasets/_Dataset.py
GeoEco/Datasets/_DatasetCollection.py
GeoEco/Datasets/_DatasetCollectionMetadata.py
GeoEco/Datasets/_DatasetMetadata.py
GeoEco/Datasets/_Grid.py
GeoEco/Datasets/_GridMetadata.py
GeoEco/Datasets/_NumpyGrid.py
GeoEco/Datasets/_NumpyGridMetadata.py
GeoEco/Datasets/_Table.py
GeoEco/Datasets/_TableMetadata.py
GeoEco/Datasets/__init__.py
GeoEco/Datasets/ArcGIS/_ArcGISRaster.py
GeoEco/Datasets/ArcGIS/_ArcGISRasterBand.py
GeoEco/Datasets/ArcGIS/_ArcGISRasterBandMetadata.py
mget3-3.4.1.dist-info/licenses/LICENSE
mget3-3.4.1.dist-info/METADATA
mget3-3.4.1.dist-info/WHEEL
mget3-3.4.1.dist-info/top_level.txt
mget3-3.4.1.dist-info/RECORD
