Metadata-Version: 2.4
Name: mget3
Version: 3.4.1
Summary: Marine Geospatial Ecology Tools: access and manipulate marine ecological and oceanographic data
Author-email: Jason Roberts <jason.roberts@duke.edu>
License: BSD 3-Clause License
Project-URL: Homepage, https://github.com/jjrob/MGET
Keywords: marine,geospatial,ecology,gis
Classifier: Development Status :: 5 - Production/Stable
Classifier: Programming Language :: Python :: 3 :: Only
Classifier: Intended Audience :: Science/Research
Classifier: License :: OSI Approved :: BSD License
Classifier: Operating System :: Microsoft :: Windows
Classifier: Operating System :: POSIX :: Linux
Classifier: Topic :: Scientific/Engineering :: Bio-Informatics
Classifier: Topic :: Scientific/Engineering :: GIS
Classifier: Topic :: Scientific/Engineering :: Oceanography
Requires-Python: <3.14,>=3.9
License-File: LICENSE
Requires-Dist: copernicusmarine
Requires-Dist: docutils
Requires-Dist: gdal
Requires-Dist: lxml
Requires-Dist: netCDF4
Requires-Dist: numpy>=1.22.4
Requires-Dist: packaging
Requires-Dist: pandas
Requires-Dist: pyarrow
Requires-Dist: pyhdf
Requires-Dist: pyparsing
Requires-Dist: python-dateutil
Requires-Dist: requests
Requires-Dist: scikit-fmm
Requires-Dist: scipy
Requires-Dist: tzlocal
Dynamic: license-file
